canary/__init__.py
canary/api.py
canary/live_stream_api.py
tests/__init__.py
tests/test_api.py
tests/test_live_stream_api.py
py_canary_2-0.6.3.dist-info/LICENSE
py_canary_2-0.6.3.dist-info/METADATA
py_canary_2-0.6.3.dist-info/WHEEL
py_canary_2-0.6.3.dist-info/top_level.txt
py_canary_2-0.6.3.dist-info/RECORD
