Metadata-Version: 2.1
Name: py-canary-2
Version: 0.6.3
Summary: Python API for the Canary App
Home-page: https://github.com/bm1549/canary
Author: Brian Marks
License: MIT
Platform: UNKNOWN
Classifier: Programming Language :: Python :: 3
Classifier: License :: OSI Approved :: MIT License
Classifier: Operating System :: OS Independent
License-File: LICENSE
Requires-Dist: requests (>=2.25.1)
